df2onehot/__init__.py
df2onehot/df2onehot.py
df2onehot/examples.py
df2onehot/utils.py
df2onehot/data/__init__.py
df2onehot/tests/__init__.py
df2onehot/tests/test_df2onehot.py
df2onehot-1.0.8.dist-info/LICENSE
df2onehot-1.0.8.dist-info/METADATA
df2onehot-1.0.8.dist-info/WHEEL
df2onehot-1.0.8.dist-info/top_level.txt
df2onehot-1.0.8.dist-info/RECORD
