Metadata-Version: 2.1
Name: df2onehot
Version: 1.0.8
Summary: Python package df2onehot is to convert a pandas dataframe into a stuctured dataframe.
Home-page: https://erdogant.github.io/df2onehot
Download-URL: https://github.com/erdogant/df2onehot/archive/1.0.8.tar.gz
Author: Erdogan Taskesen
Author-email: erdogant@gmail.com
Classifier: Programming Language :: Python :: 3
Classifier: License :: OSI Approved :: MIT License
Classifier: Operating System :: OS Independent
Requires-Python: >=3
License-File: LICENSE
Requires-Dist: packaging
Requires-Dist: scikit-learn
Requires-Dist: numpy
Requires-Dist: pandas
Requires-Dist: tqdm
Requires-Dist: datazets
